aiogram_fastapi_server/__init__.py
aiogram_fastapi_server-0.1.2.dist-info/LICENSE
aiogram_fastapi_server-0.1.2.dist-info/METADATA
aiogram_fastapi_server-0.1.2.dist-info/WHEEL
aiogram_fastapi_server-0.1.2.dist-info/RECORD
