Metadata-Version: 2.1
Name: aiogram-fastapi-server
Version: 0.1.2
Summary: Handle webhook requests with FastAPI instead of aiohttp
License: MIT
Author: Snimshchikov Ilya
Author-email: snimshchikov.ilya@gmail.com
Requires-Python: >=3.8,<4.0
Classifier: License :: OSI Approved :: MIT License
Classifier: Programming Language :: Python :: 3
Classifier: Programming Language :: Python :: 3.8
Classifier: Programming Language :: Python :: 3.9
Classifier: Programming Language :: Python :: 3.10
Classifier: Programming Language :: Python :: 3.11
Requires-Dist: aiogram (>=3.0.0b1,<4.0.0)
Requires-Dist: fastapi
